README.txt
bootstrap.py
buildout.cfg
setup.cfg
setup.py
collective/__init__.py
collective.cssgridsystem.egg-info/PKG-INFO
collective.cssgridsystem.egg-info/SOURCES.txt
collective.cssgridsystem.egg-info/dependency_links.txt
collective.cssgridsystem.egg-info/entry_points.txt
collective.cssgridsystem.egg-info/namespace_packages.txt
collective.cssgridsystem.egg-info/not-zip-safe
collective.cssgridsystem.egg-info/paster_plugins.txt
collective.cssgridsystem.egg-info/requires.txt
collective.cssgridsystem.egg-info/top_level.txt
collective/cssgridsystem/__init__.py
collective/cssgridsystem/configure.zcml
collective/cssgridsystem/tests.py
collective/cssgridsystem/960/docs/GPL_license.txt
collective/cssgridsystem/960/docs/MIT_license.txt
collective/cssgridsystem/960/docs/README.txt
collective/cssgridsystem/960/docs/demo.html
collective/cssgridsystem/960/docs/demo_24_col.html
collective/cssgridsystem/960/docs/rtl_demo.html
collective/cssgridsystem/960/docs/rtl_demo_24_col.html
collective/cssgridsystem/960/resources/960.css
collective/cssgridsystem/960/resources/960_24_col.css
collective/cssgridsystem/960/resources/reset.css
collective/cssgridsystem/960/resources/rtl_960.css
collective/cssgridsystem/960/resources/rtl_960_24_col.css
collective/cssgridsystem/960/resources/rtl_text.css
collective/cssgridsystem/960/resources/text.css
collective/cssgridsystem/960/resources/src/960.css
collective/cssgridsystem/960/resources/src/960_24_col.css
collective/cssgridsystem/960/resources/src/demo.css
collective/cssgridsystem/960/resources/src/reset.css
collective/cssgridsystem/960/resources/src/rtl_960.css
collective/cssgridsystem/960/resources/src/rtl_960_24_col.css
collective/cssgridsystem/960/resources/src/rtl_text.css
collective/cssgridsystem/960/resources/src/text.css
collective/cssgridsystem/blueprintcss/docs/AUTHORS.textile
collective/cssgridsystem/blueprintcss/docs/CHANGELOG
collective/cssgridsystem/blueprintcss/docs/LICENSE
collective/cssgridsystem/blueprintcss/docs/README.textile
collective/cssgridsystem/blueprintcss/docs/TUTORIAL.textile
collective/cssgridsystem/blueprintcss/resources/ie.css
collective/cssgridsystem/blueprintcss/resources/print.css
collective/cssgridsystem/blueprintcss/resources/screen.css
collective/cssgridsystem/blueprintcss/resources/plugins/buttons/readme.txt
collective/cssgridsystem/blueprintcss/resources/plugins/buttons/screen.css
