Metadata-Version: 1.0
Name: collective.cssgridsystem
Version: 1.0
Summary: 960CSS And Blue print packaged as zope browser resource
Home-page: http://svn.plone.org/svn/collective/collective.cssgridsystem
Author: JeanMichel FRANCOIS aka toutpt
Author-email: toupt@gmail.com
License: GPL
Keywords: css zope plone
Platform: UNKNOWN
Classifier: Framework :: Plone
Classifier: Programming Language :: Python
